haws/__init__.py
haws/main.py
haws/commands/__init__.py
haws/commands/cost.py
haws/commands/credentials.py
haws/commands/org.py
haws/commands/policies.py
haws/commands/run.py
haws/commands/setup.py
haws/config/__init__.py
haws/config/leanix_policies.py
haws/config/logger.ini
haws/config/scan_config_template.json
haws/exceptions/__init__.py
haws/exceptions/authentication.py
haws/exceptions/billing.py
haws/services/__init__.py
haws/services/auth.py
haws/services/leanix_policies.py
haws/services/lx_api_connector.py
haws/services/runtime_helper.py
haws/services/setup_helper.py
haws/services/aws/__init__.py
haws/services/aws/cost_allocation_tags.py
haws/services/aws/credential_check.py
haws/services/aws/organization_check.py
haws/services/aws/policy_check.py
haws-1.0.11.dist-info/LICENSE.txt
haws-1.0.11.dist-info/METADATA
haws-1.0.11.dist-info/WHEEL
haws-1.0.11.dist-info/entry_points.txt
haws-1.0.11.dist-info/top_level.txt
haws-1.0.11.dist-info/RECORD
